praison/__init__.py
praison/__main__.py
praison/ezhil/.idea/inspectionProfiles/Project_Default.xml
praison/ezhil/.idea/inspectionProfiles/profiles_settings.xml
praison/ezhil/EZTurtle.py
praison/ezhil/EZWeb.py
praison/ezhil/ExprsParser.py
praison/ezhil/Interpreter.py
praison/ezhil/Makefile
praison/ezhil/__init__.py
praison/ezhil/__main__.py
praison/ezhil/ast.py
praison/ezhil/errors.py
praison/ezhil/exprs.py
praison/ezhil/ezhil.py
praison/ezhil/ezhil_library.py
praison/ezhil/ezhil_messages.py
praison/ezhil/ezhil_parser.py
praison/ezhil/ezhil_program_utils.py
praison/ezhil/ezhil_scanner.py
praison/ezhil/ezhil_serializer.py
praison/ezhil/ezhil_transforms.py
praison/ezhil/ezhil_visualizer.py
praison/ezhil/prettify.py
praison/ezhil/profile.py
praison/ezhil/runtime.py
praison/ezhil/scanner.py
praison/ezhil/theme.py
praison/ezhil/transform.py
praison-0.2.4.dist-info/LICENSE
praison-0.2.4.dist-info/METADATA
praison-0.2.4.dist-info/WHEEL
praison-0.2.4.dist-info/entry_points.txt
praison-0.2.4.dist-info/RECORD
