Metadata-Version: 2.1
Name: praison
Version: 0.2.4
Summary: 
Author: MervinPraison
Requires-Python: >=3.8,<4.0
Classifier: Programming Language :: Python :: 3
Classifier: Programming Language :: Python :: 3.8
Classifier: Programming Language :: Python :: 3.9
Classifier: Programming Language :: Python :: 3.10
Classifier: Programming Language :: Python :: 3.11
Requires-Dist: open-tamil (>=1.1,<2.0)
